{
	"_total_users" : "4",
	"_return_limit" : "3",
	"data" : [
		{
			"_id" : "5c728654-a98b-4b8e-b256-874b1fd93e70",
			"first_name" : "Dennis",
			"second_name" : "Ritchie",
			"born" : "September 9, 1941",
			"address" : "Berkeley Heights, New Jersey, U.S."
		},
		{
			"_id" : "c634962d-b601-4943-b197-74d52baa93cc",
			"first_name" : "Linus",
			"second_name" : "Torvalds",
			"born" : "December 28, 1969",
			"address" : "Helsinki, Finland"
		},
		{
			"_id" : "c7218e56-0474-4370-9560-c66e7b6ec43a",
			"first_name" : "Richard",
			"second_name" : "Stallman",
			"born" : "March 16, 1953",
			"address" : "Massachusetts Institute of Technology, Cambridge, Massachusetts, United States"
		},
		{
			"_id" : "5c728654-a98b-4b8e-b256-874b1fd93e70",
			"first_name" : "Tim",
			"second_name" : "Berners-Lee",
			"born" : "June 8, 1955",
			"address" : "London, England"
		}
	]
}